LICENSE.txt
MANIFEST.in
README.md
requirements.txt
setup.py
epic2cf/__init__.py
epic2cf/data.py
epic2cf.egg-info/PKG-INFO
epic2cf.egg-info/SOURCES.txt
epic2cf.egg-info/dependency_links.txt
epic2cf.egg-info/requires.txt
epic2cf.egg-info/top_level.txt