Metadata-Version: 1.1
Name: epic2cf
Version: 0.0.2
Summary: A simple python library to find the CF standard name equivalent of an EPIC code.
Home-page: https://github.com/axiom-data-science/epic2cf
Author: Kyle Wilcox
Author-email: kyle@axiomdatascience.com
License: MIT
Platform: UNKNOWN
Classifier: Development Status :: 3 - Alpha
Classifier: Intended Audience :: Developers
Classifier: Intended Audience :: Science/Research
Classifier: License :: OSI Approved :: MIT License
Classifier: Operating System :: POSIX :: Linux
Classifier: Programming Language :: Python
Classifier: Topic :: Scientific/Engineering
